LICENSE
MANIFEST.in
NOTICE
setup.py
grolt/__init__.py
grolt/__main__.py
grolt/compat.py
grolt/images.py
grolt.egg-info/PKG-INFO
grolt.egg-info/SOURCES.txt
grolt.egg-info/dependency_links.txt
grolt.egg-info/entry_points.txt
grolt.egg-info/requires.txt
grolt.egg-info/top_level.txt
grolt/security/__init__.py
grolt/security/_cryptography.py